Metadata-Version: 2.4
Name: mseep-amazing-marvin-mcp
Version: 1.0.3
Summary: Amazing Marvin Model Context Provider
Author-email: mseep <support@skydeck.ai>
License-Expression: MIT
Project-URL: Homepage, https://github.com/bgheneti/Amazing-Marvin-MCP
Project-URL: Bug Tracker, https://github.com/bgheneti/Amazing-Marvin-MCP/issues
Classifier: Programming Language :: Python :: 3
Classifier: Programming Language :: Python :: 3.10
Classifier: Programming Language :: Python :: 3.11
Classifier: Programming Language :: Python :: 3.12
Classifier: Operating System :: OS Independent
Requires-Python: >=3.10
Requires-Dist: fastapi>=0.68.0
Requires-Dist: fastmcp>=0.1.0
Requires-Dist: requests>=2.25.1
Requires-Dist: uvicorn>=0.15.0
Requires-Dist: pydantic>=2.0.0
Requires-Dist: pydantic-settings>=2.0.0
Requires-Dist: python-dotenv>=0.19.0
Provides-Extra: dev
Requires-Dist: pytest>=6.0.0; extra == "dev"
Requires-Dist: ruff>=0.12.0; extra == "dev"
Requires-Dist: mypy>=0.812; extra == "dev"
Requires-Dist: pre-commit>=3.0.0; extra == "dev"
Requires-Dist: types-requests>=2.25.0; extra == "dev"
